LICENSE
MANIFEST.in
README.md
setup.py
django_things.egg-info/PKG-INFO
django_things.egg-info/SOURCES.txt
django_things.egg-info/dependency_links.txt
django_things.egg-info/entry_points.txt
django_things.egg-info/requires.txt
django_things.egg-info/top_level.txt
things/__init__.py
things/admin.py
things/attrs.py
things/context_processors.py
things/feeds.py
things/forms.py
things/models.py
things/renderers.py
things/s3_storages.py
things/settings.py
things/tests.py
things/types.py
things/urls.py
things/utils.py
things/views.py
things/bin/__init__.py
things/bin/create_things_project.py
things/bin/update_things_project.py
things/management/__init__.py
things/management/commands/__init__.py
things/management/commands/clear_static_builds.py
things/management/commands/rebuild_static_site.py
things/pages/__init__.py
things/pages/admin.py
things/pages/models.py
things/pages/templates/pages/page_detail.html
things/project_template/.env_example
things/project_template/.gitignore
things/project_template/Procfile
things/project_template/manage.py
things/project_template/requirements.txt
things/project_template/apps/posts/__init__.py
things/project_template/apps/posts/admin.py
things/project_template/apps/posts/models.py
things/project_template/apps/posts/urls.py
things/project_template/conf/__init__.py
things/project_template/conf/settings.py
things/project_template/conf/urls.py
things/project_template/conf/wsgi.py
things/project_template/requirements/common.txt
things/project_template/requirements/dev.txt
things/project_template/requirements/prod.txt
things/project_template/themes/default_theme/static/css/style.css
things/project_template/themes/default_theme/static/css/style.less
things/project_template/themes/default_theme/templates/footer.html
things/project_template/themes/default_theme/templates/header.html
things/project_template/themes/default_theme/templates/home.html
things/project_template/themes/default_theme/templates/interior.html
things/snippets/__init__.py
things/snippets/admin.py
things/snippets/forms.py
things/snippets/models.py
things/snippets/utils.py
things/snippets/templates/_snippet.html
things/snippets/templatetags/__init__.py
things/snippets/templatetags/snippet_tags.py
